README.md
setup.py
merlin/__init__.py
merlin/candidate_selection.py
merlin/discords_refinement.py
merlin/distance.py
merlin/drag.py
merlin/merlin.py
merlin_ts.egg-info/PKG-INFO
merlin_ts.egg-info/SOURCES.txt
merlin_ts.egg-info/dependency_links.txt
merlin_ts.egg-info/requires.txt
merlin_ts.egg-info/top_level.txt